pystrata/__init__.py
pystrata/motion.py
pystrata/output.py
pystrata/propagation.py
pystrata/site.py
pystrata/tools.py
pystrata/variation.py
pystrata/data/published_curves.toml
pystrata-0.5.4.dist-info/METADATA
pystrata-0.5.4.dist-info/WHEEL
pystrata-0.5.4.dist-info/licenses/AUTHORS.md
pystrata-0.5.4.dist-info/licenses/LICENSE
pystrata-0.5.4.dist-info/RECORD
