Metadata-Version: 2.3
Name: pyStrata
Version: 0.5.4
Summary: Site response analysis with Python.
Project-URL: Homepage, https://github.com/arkottke/pystrata
Project-URL: Documentation, https://pystrata.readthedocs.io
Author-email: Albert Kottke <albert.kottke@gmail.com>
License-Expression: MIT
License-File: AUTHORS.md
License-File: LICENSE
Requires-Python: >=3.8
Requires-Dist: matplotlib
Requires-Dist: numba
Requires-Dist: numpy
Requires-Dist: pykooh
Requires-Dist: pyrvt
Requires-Dist: scipy
Requires-Dist: setuptools
Requires-Dist: tomli
